agent_observability_crewai/__init__.py
agent_observability_crewai/callbacks.py
agent_observability_crewai/tool.py
agent_observability_crewai-1.2.1.dist-info/licenses/LICENSE
tests/__init__.py
agent_observability_crewai-1.2.1.dist-info/METADATA
agent_observability_crewai-1.2.1.dist-info/WHEEL
agent_observability_crewai-1.2.1.dist-info/top_level.txt
agent_observability_crewai-1.2.1.dist-info/RECORD
