Metadata-Version: 2.4
Name: agent-observability-crewai
Version: 1.2.1
Summary: CrewAI integration for Agent Observability - multi-agent logging, cost tracking, and compliance
Home-page: https://api-production-0c55.up.railway.app
Author: Agent Observability Team
Author-email: hello@agentobs.io
Project-URL: Homepage, https://api-production-0c55.up.railway.app
Project-URL: Documentation, https://api-production-0c55.up.railway.app/docs
Keywords: crewai,multi-agent,observability,logging,compliance,ai-agent,cost-tracking,crew
Classifier: Development Status :: 4 - Beta
Classifier: Intended Audience :: Developers
Classifier: Topic :: Software Development :: Libraries :: Python Modules
Classifier: Topic :: System :: Monitoring
Classifier: License :: OSI Approved :: MIT License
Classifier: Programming Language :: Python :: 3
Classifier: Programming Language :: Python :: 3.10
Classifier: Programming Language :: Python :: 3.11
Classifier: Programming Language :: Python :: 3.12
Requires-Python: >=3.10
License-File: LICENSE
Requires-Dist: agent-observability>=1.1.0
Requires-Dist: pydantic>=2.0.0
Provides-Extra: crewai
Requires-Dist: crewai>=0.28.0; extra == "crewai"
Requires-Dist: crewai-tools>=0.2.0; extra == "crewai"
Dynamic: author
Dynamic: author-email
Dynamic: classifier
Dynamic: description
Dynamic: description-content-type
Dynamic: home-page
Dynamic: keywords
Dynamic: license-file
Dynamic: project-url
Dynamic: provides-extra
Dynamic: requires-dist
Dynamic: requires-python
Dynamic: summary
